pylj/__init__.py
pylj/_testutils.py
pylj/forcefields.py
pylj/mc.py
pylj/md.py
pylj/pairwise.py
pylj/sample.py
pylj/util.py
pylj/tests/__init__.py
pylj/tests/test_forcefields.py
pylj/tests/test_mc.py
pylj/tests/test_md.py
pylj/tests/test_pairwise.py
pylj/tests/test_util.py
pylj-1.5.2.dist-info/LICENSE
pylj-1.5.2.dist-info/METADATA
pylj-1.5.2.dist-info/WHEEL
pylj-1.5.2.dist-info/top_level.txt
pylj-1.5.2.dist-info/RECORD
