Metadata-Version: 2.1
Name: pylj
Version: 1.5.2
Summary: Simple teaching tool for classical MD simulation
Author: Andrew R. McCluskey
Author-email: arm61@bath.ac.uk
License: MIT
Classifier: Development Status :: 5 - Production/Stable
Classifier: Framework :: Jupyter
Classifier: Intended Audience :: Science/Research
Classifier: License :: OSI Approved :: MIT License
Classifier: Natural Language :: English
Classifier: Operating System :: OS Independent
Classifier: Programming Language :: Python :: 2.7
Classifier: Programming Language :: Python :: 3.5
Classifier: Programming Language :: Python :: 3.6
Classifier: Programming Language :: Python :: 3.7
Classifier: Topic :: Scientific/Engineering
Classifier: Topic :: Scientific/Engineering :: Chemistry
Classifier: Topic :: Scientific/Engineering :: Physics
License-File: LICENSE
Requires-Dist: jupyter
Requires-Dist: numpy
Requires-Dist: matplotlib
Requires-Dist: cython
